modal/__init__.py
modal_py-0.0.0.dist-info/LICENSE
modal_py-0.0.0.dist-info/METADATA
modal_py-0.0.0.dist-info/WHEEL
modal_py-0.0.0.dist-info/top_level.txt
modal_py-0.0.0.dist-info/RECORD
